{
  "config": {
    "model_short": "llama",
    "task_name": "somo",
    "dataset": {
      "train": "cache/llama/somo_train/",
      "test": "cache/llama/somo_test/"
    },
    "mdl": {
      "batch_size": 64,
      "probe_type": "mlp",
      "probe_hidden_size": [
        16
      ],
      "num_classes": 2,
      "init_strategy": "gamma",
      "init_gamma": 1.0,
      "optimizer": "adamw",
      "train_epochs": 10,
      "lr": 0.001,
      "seed": 442,
      "early_stopping_gap": 3,
      "split_num": 5,
      "split_ratio": 2.0
    },
    "out_dir": "init_results/llama/somo/hidden-16/seed-442/strategy-gamma/gamma-1.0/opt-adamw/2026-04-22_05-53-36"
  },
  "train_meta": {
    "dataset": "compling/somo",
    "split": "train",
    "text_col": "text",
    "model": "meta-llama/Meta-Llama-3.1-8B",
    "max_len": 64,
    "hidden_size": 4096,
    "num_hidden_layers": 32,
    "num_states": 33,
    "memmap_file": "last_token_hidden_states.memmap",
    "dtype": "float32",
    "shape": [
      15000,
      33,
      4096
    ]
  },
  "test_meta": {
    "dataset": "compling/somo",
    "split": "test",
    "text_col": "text",
    "model": "meta-llama/Meta-Llama-3.1-8B",
    "max_len": 64,
    "hidden_size": 4096,
    "num_hidden_layers": 32,
    "num_states": 33,
    "memmap_file": "last_token_hidden_states.memmap",
    "dtype": "float32",
    "shape": [
      10000,
      33,
      4096
    ]
  },
  "splits": [
    484,
    968,
    1936,
    3872,
    7740
  ],
  "mdl_sum_ce": {
    "0": 10060.300895690918,
    "1": 10060.404235839844,
    "2": 10058.555404663086,
    "3": 10006.556215763092,
    "4": 9731.834620952606,
    "5": 9566.342740535736,
    "6": 9478.23371219635,
    "7": 9224.027480125427,
    "8": 8910.426104545593,
    "9": 8495.794826984406,
    "10": 8059.786470413208,
    "11": 8099.438659667969,
    "12": 8117.462129116058,
    "13": 8075.671910524368,
    "14": 8109.5235414505005,
    "15": 8262.412350654602,
    "16": 8438.57158255577,
    "17": 8392.868933200836,
    "18": 8474.970502376556,
    "19": 8546.891674995422,
    "20": 8654.580911636353,
    "21": 8574.551609992981,
    "22": 8686.867510318756,
    "23": 8681.982734680176,
    "24": 8725.384161949158,
    "25": 9568.95900774002,
    "26": 8967.139472961426,
    "27": 8720.387863636017,
    "28": 8822.857679843903,
    "29": 8907.963174819946,
    "30": 8869.53287935257,
    "31": 8842.008149147034,
    "32": 8880.089104175568
  },
  "mdl_nll": {
    "0": 0.6930491110285835,
    "1": 0.693056230079901,
    "2": 0.6929288650222573,
    "3": 0.6893466668340515,
    "4": 0.6704212331876968,
    "5": 0.659020580086507,
    "6": 0.6529507930694647,
    "7": 0.6354386525299963,
    "8": 0.6138348101781202,
    "9": 0.5852710682684215,
    "10": 0.5552346700477547,
    "11": 0.5579662895885897,
    "12": 0.5592079174094832,
    "13": 0.5563290100939906,
    "14": 0.5586610320646528,
    "15": 0.5691934658759026,
    "16": 0.5813289875003975,
    "17": 0.578180554780989,
    "18": 0.5838364909325267,
    "19": 0.588791104642837,
    "20": 0.5962097624439482,
    "21": 0.59069658376915,
    "22": 0.5984339701239154,
    "23": 0.5980974603665042,
    "24": 0.601087363044169,
    "25": 0.6592008134293208,
    "26": 0.617741765841928,
    "27": 0.6007431705453304,
    "28": 0.6078022650760473,
    "29": 0.6136651401777312,
    "30": 0.6110176962904774,
    "31": 0.6091215313548521,
    "32": 0.6117449093535111
  },
  "stopping_epochs_per_stage": {
    "0": [
      1,
      10,
      6,
      1
    ],
    "1": [
      1,
      2,
      2,
      5
    ],
    "2": [
      1,
      1,
      8,
      1
    ],
    "3": [
      2,
      2,
      10,
      10
    ],
    "4": [
      4,
      10,
      10,
      9
    ],
    "5": [
      3,
      10,
      9,
      7
    ],
    "6": [
      8,
      10,
      10,
      7
    ],
    "7": [
      10,
      10,
      10,
      8
    ],
    "8": [
      4,
      9,
      10,
      7
    ],
    "9": [
      10,
      10,
      9,
      10
    ],
    "10": [
      10,
      9,
      10,
      6
    ],
    "11": [
      10,
      10,
      10,
      4
    ],
    "12": [
      10,
      9,
      10,
      10
    ],
    "13": [
      10,
      6,
      8,
      6
    ],
    "14": [
      10,
      10,
      9,
      7
    ],
    "15": [
      1,
      10,
      9,
      6
    ],
    "16": [
      9,
      8,
      9,
      8
    ],
    "17": [
      9,
      8,
      9,
      7
    ],
    "18": [
      5,
      10,
      7,
      6
    ],
    "19": [
      10,
      9,
      10,
      4
    ],
    "20": [
      9,
      7,
      9,
      7
    ],
    "21": [
      9,
      10,
      10,
      8
    ],
    "22": [
      4,
      10,
      5,
      4
    ],
    "23": [
      8,
      8,
      5,
      10
    ],
    "24": [
      10,
      9,
      10,
      7
    ],
    "25": [
      6,
      6,
      8,
      6
    ],
    "26": [
      2,
      10,
      7,
      8
    ],
    "27": [
      1,
      10,
      8,
      5
    ],
    "28": [
      8,
      9,
      10,
      5
    ],
    "29": [
      5,
      9,
      8,
      2
    ],
    "30": [
      8,
      4,
      10,
      7
    ],
    "31": [
      10,
      8,
      7,
      7
    ],
    "32": [
      8,
      4,
      4,
      9
    ]
  },
  "test_acc": {
    "0": 0.5013,
    "1": 0.5009,
    "2": 0.5013,
    "3": 0.5497,
    "4": 0.6091,
    "5": 0.6414,
    "6": 0.6483,
    "7": 0.6563,
    "8": 0.6958,
    "9": 0.7075,
    "10": 0.7281,
    "11": 0.7279,
    "12": 0.731,
    "13": 0.7201,
    "14": 0.7322,
    "15": 0.7042,
    "16": 0.7157,
    "17": 0.7157,
    "18": 0.7214,
    "19": 0.7209,
    "20": 0.7192,
    "21": 0.7135,
    "22": 0.668,
    "23": 0.7111,
    "24": 0.6899,
    "25": 0.6681,
    "26": 0.6845,
    "27": 0.6939,
    "28": 0.6898,
    "29": 0.7033,
    "30": 0.6802,
    "31": 0.6993,
    "32": 0.69
  },
  "test_loss": {
    "0": 0.6931470881462097,
    "1": 0.6937508669853211,
    "2": 0.693181036567688,
    "3": 0.686687370967865,
    "4": 0.6553259545326233,
    "5": 0.6329324998855591,
    "6": 0.6292747170448303,
    "7": 0.6168064964294434,
    "8": 0.5883526198387146,
    "9": 0.5735960149765015,
    "10": 0.547114760684967,
    "11": 0.5436122305870056,
    "12": 0.5410931416988373,
    "13": 0.5511421866893769,
    "14": 0.5413302377700806,
    "15": 0.5792494236946106,
    "16": 0.5601116729736328,
    "17": 0.5593142405986786,
    "18": 0.5546390412807465,
    "19": 0.5527906418800353,
    "20": 0.5572889976978302,
    "21": 0.560632984161377,
    "22": 0.6161168870925904,
    "23": 0.5677331727981567,
    "24": 0.595394102191925,
    "25": 0.6081351538658142,
    "26": 0.611317622756958,
    "27": 0.5876071673393249,
    "28": 0.5923413970947266,
    "29": 0.5802414412498474,
    "30": 0.6164745341300965,
    "31": 0.5750948709964753,
    "32": 0.5941298445701599
  },
  "drift_final_total_l2": {
    "0": 1.3323346376419067,
    "1": 7.158326148986816,
    "2": 1.839105486869812,
    "3": 11.224465370178223,
    "4": 14.277207374572754,
    "5": 13.176990509033203,
    "6": 7.954600811004639,
    "7": 9.295084953308105,
    "8": 11.866501808166504,
    "9": 15.256148338317871,
    "10": 14.171335220336914,
    "11": 12.525139808654785,
    "12": 13.414039611816406,
    "13": 12.01385498046875,
    "14": 15.064711570739746,
    "15": 13.413142204284668,
    "16": 13.058368682861328,
    "17": 11.077729225158691,
    "18": 11.387728691101074,
    "19": 11.514372825622559,
    "20": 8.478669166564941,
    "21": 8.25912094116211,
    "22": 10.221364974975586,
    "23": 8.72555923461914,
    "24": 10.102417945861816,
    "25": 8.522908210754395,
    "26": 10.429512977600098,
    "27": 9.05840015411377,
    "28": 10.690040588378906,
    "29": 8.271834373474121,
    "30": 8.531086921691895,
    "31": 7.84722900390625,
    "32": 5.1660990715026855
  },
  "probe_type": "mlp",
  "probe_hidden_size": [
    16
  ],
  "init_strategy": "gamma",
  "init_gamma": 1.0,
  "effective_lr": 0.001,
  "lr_scaling_rule": "base_lr",
  "bias_init": "zero",
  "forward_prefactor": 1.0,
  "probe_width": 16,
  "L": 33,
  "D": 4096
}