{
  "config": {
    "model_short": "llama",
    "task_name": "somo",
    "dataset": {
      "train": "cache/llama/somo_train/",
      "test": "cache/llama/somo_test/"
    },
    "mdl": {
      "batch_size": 64,
      "probe_type": "mlp",
      "probe_hidden_size": [
        512
      ],
      "num_classes": 2,
      "init_strategy": "gamma_second_zero",
      "init_gamma": 1.9,
      "optimizer": "adamw",
      "train_epochs": 10,
      "lr": 0.001,
      "seed": 442,
      "early_stopping_gap": 3,
      "split_num": 5,
      "split_ratio": 2.0
    },
    "out_dir": "init_results/llama/somo/hidden-512/seed-442/strategy-gamma_second_zero/gamma-1.9/opt-adamw/2026-04-25_03-25-08"
  },
  "train_meta": {
    "dataset": "compling/somo",
    "split": "train",
    "text_col": "text",
    "model": "meta-llama/Meta-Llama-3.1-8B",
    "max_len": 64,
    "hidden_size": 4096,
    "num_hidden_layers": 32,
    "num_states": 33,
    "memmap_file": "last_token_hidden_states.memmap",
    "dtype": "float32",
    "shape": [
      15000,
      33,
      4096
    ]
  },
  "test_meta": {
    "dataset": "compling/somo",
    "split": "test",
    "text_col": "text",
    "model": "meta-llama/Meta-Llama-3.1-8B",
    "max_len": 64,
    "hidden_size": 4096,
    "num_hidden_layers": 32,
    "num_states": 33,
    "memmap_file": "last_token_hidden_states.memmap",
    "dtype": "float32",
    "shape": [
      10000,
      33,
      4096
    ]
  },
  "splits": [
    484,
    968,
    1936,
    3872,
    7740
  ],
  "mdl_sum_ce": {
    "0": 10059.937412261963,
    "1": 10059.34544467926,
    "2": 10060.96813249588,
    "3": 10058.945186138153,
    "4": 9860.778751373291,
    "5": 9470.332045555115,
    "6": 9526.89611530304,
    "7": 9237.983799934387,
    "8": 8895.523119926453,
    "9": 8565.38771533966,
    "10": 8105.045216560364,
    "11": 8068.393058300018,
    "12": 8089.375333070755,
    "13": 8134.136927604675,
    "14": 8172.331401348114,
    "15": 8257.576040267944,
    "16": 8343.771750211716,
    "17": 8462.834369659424,
    "18": 8504.643377304077,
    "19": 8582.484281539917,
    "20": 8588.990821838379,
    "21": 8626.711167812347,
    "22": 8630.363458633423,
    "23": 8667.083595752716,
    "24": 8744.83932876587,
    "25": 8712.508754730225,
    "26": 8781.620645523071,
    "27": 8805.3180975914,
    "28": 8814.614032745361,
    "29": 8904.49194574356,
    "30": 8753.025660991669,
    "31": 8777.83456325531,
    "32": 8927.156835079193
  },
  "mdl_nll": {
    "0": 0.6930240708364538,
    "1": 0.6929832904849311,
    "2": 0.6930950766392863,
    "3": 0.6929557168736672,
    "4": 0.6793041300202046,
    "5": 0.6524064511955852,
    "6": 0.6563031217486249,
    "7": 0.6364000964407817,
    "8": 0.6128081510007201,
    "9": 0.5900652876370668,
    "10": 0.5583525224965806,
    "11": 0.5558275735946554,
    "12": 0.5572730320384923,
    "13": 0.5603566359606418,
    "14": 0.5629878342069519,
    "15": 0.5688602948655238,
    "16": 0.5747982743325789,
    "17": 0.5830004388026607,
    "18": 0.5858806404866408,
    "19": 0.5912430615555192,
    "20": 0.5916912938714783,
    "21": 0.5942898296922257,
    "22": 0.5945414341852729,
    "23": 0.5970710661168859,
    "24": 0.6024276197827135,
    "25": 0.6002003826625947,
    "26": 0.604961466349068,
    "27": 0.6065939720027143,
    "28": 0.6072343643390301,
    "29": 0.6134260089379692,
    "30": 0.6029915721267338,
    "31": 0.6047006450299883,
    "32": 0.6149873818599609
  },
  "stopping_epochs_per_stage": {
    "0": [
      1,
      1,
      9,
      5
    ],
    "1": [
      1,
      1,
      7,
      2
    ],
    "2": [
      2,
      1,
      3,
      1
    ],
    "3": [
      1,
      2,
      4,
      1
    ],
    "4": [
      4,
      7,
      8,
      9
    ],
    "5": [
      1,
      10,
      10,
      9
    ],
    "6": [
      1,
      10,
      10,
      3
    ],
    "7": [
      1,
      10,
      6,
      10
    ],
    "8": [
      2,
      8,
      10,
      6
    ],
    "9": [
      7,
      7,
      7,
      4
    ],
    "10": [
      5,
      6,
      4,
      4
    ],
    "11": [
      9,
      9,
      8,
      5
    ],
    "12": [
      9,
      10,
      6,
      5
    ],
    "13": [
      6,
      5,
      4,
      4
    ],
    "14": [
      8,
      6,
      6,
      4
    ],
    "15": [
      8,
      5,
      5,
      5
    ],
    "16": [
      8,
      4,
      3,
      5
    ],
    "17": [
      2,
      8,
      7,
      6
    ],
    "18": [
      2,
      6,
      6,
      4
    ],
    "19": [
      7,
      5,
      6,
      4
    ],
    "20": [
      5,
      8,
      7,
      5
    ],
    "21": [
      6,
      6,
      8,
      6
    ],
    "22": [
      6,
      6,
      6,
      6
    ],
    "23": [
      8,
      5,
      7,
      6
    ],
    "24": [
      4,
      4,
      5,
      8
    ],
    "25": [
      4,
      7,
      8,
      5
    ],
    "26": [
      2,
      4,
      6,
      6
    ],
    "27": [
      6,
      6,
      6,
      3
    ],
    "28": [
      9,
      7,
      5,
      6
    ],
    "29": [
      6,
      4,
      4,
      2
    ],
    "30": [
      5,
      5,
      6,
      4
    ],
    "31": [
      7,
      5,
      7,
      7
    ],
    "32": [
      5,
      2,
      4,
      5
    ]
  },
  "test_acc": {
    "0": 0.5013,
    "1": 0.4947,
    "2": 0.5235,
    "3": 0.5397,
    "4": 0.6094,
    "5": 0.6379,
    "6": 0.6427,
    "7": 0.6558,
    "8": 0.6537,
    "9": 0.706,
    "10": 0.7307,
    "11": 0.7002,
    "12": 0.7162,
    "13": 0.6994,
    "14": 0.7188,
    "15": 0.7272,
    "16": 0.725,
    "17": 0.7198,
    "18": 0.722,
    "19": 0.7064,
    "20": 0.7198,
    "21": 0.7146,
    "22": 0.7115,
    "23": 0.7051,
    "24": 0.702,
    "25": 0.6823,
    "26": 0.7041,
    "27": 0.6787,
    "28": 0.6959,
    "29": 0.7007,
    "30": 0.685,
    "31": 0.6965,
    "32": 0.6793
  },
  "test_loss": {
    "0": 0.6931481773376464,
    "1": 0.6939331901550293,
    "2": 0.6919427486419678,
    "3": 0.6873467699050904,
    "4": 0.654990097618103,
    "5": 0.6417556331634522,
    "6": 0.6332184643745422,
    "7": 0.6324256107330323,
    "8": 0.6361692016601562,
    "9": 0.5831690690040588,
    "10": 0.5492706915855408,
    "11": 0.6063185387849808,
    "12": 0.5695899299621582,
    "13": 0.5955666520118713,
    "14": 0.5672980523109437,
    "15": 0.5691917839050293,
    "16": 0.5675382676124573,
    "17": 0.5603894715309143,
    "18": 0.5540856930732727,
    "19": 0.5879460329055786,
    "20": 0.5588297897338868,
    "21": 0.5655410562515258,
    "22": 0.5624204469680786,
    "23": 0.5723243779182434,
    "24": 0.5837556480407715,
    "25": 0.593731100654602,
    "26": 0.5777614841461182,
    "27": 0.6430146525382996,
    "28": 0.6026177677154541,
    "29": 0.5838963958740234,
    "30": 0.6246643137931823,
    "31": 0.5864013367652893,
    "32": 0.5958506841659545
  },
  "drift_final_total_l2": {
    "0": 7.573962211608887,
    "1": 9.17403793334961,
    "2": 14.43399715423584,
    "3": 13.224207878112793,
    "4": 15.028783798217773,
    "5": 24.94508934020996,
    "6": 21.00641632080078,
    "7": 27.948326110839844,
    "8": 20.946796417236328,
    "9": 33.94620132446289,
    "10": 48.90327453613281,
    "11": 47.87638854980469,
    "12": 37.3060302734375,
    "13": 34.77837371826172,
    "14": 28.394317626953125,
    "15": 46.675777435302734,
    "16": 30.2198486328125,
    "17": 33.42816925048828,
    "18": 25.26392936706543,
    "19": 26.121105194091797,
    "20": 17.619199752807617,
    "21": 29.13294219970703,
    "22": 19.281814575195312,
    "23": 18.912229537963867,
    "24": 21.918930053710938,
    "25": 24.336639404296875,
    "26": 21.02219581604004,
    "27": 24.97018051147461,
    "28": 18.99002456665039,
    "29": 22.289623260498047,
    "30": 22.480087280273438,
    "31": 18.38983917236328,
    "32": 15.133679389953613
  },
  "probe_type": "mlp",
  "probe_hidden_size": [
    512
  ],
  "init_strategy": "gamma_second_zero",
  "init_gamma": 1.9,
  "effective_lr": 0.001,
  "lr_scaling_rule": "base_lr",
  "bias_init": "zero",
  "forward_prefactor": 1.0,
  "probe_width": 512,
  "L": 33,
  "D": 4096
}