{
  "config": {
    "model_short": "llama",
    "task_name": "somo",
    "dataset": {
      "train": "cache/llama/somo_train/",
      "test": "cache/llama/somo_test/"
    },
    "mdl": {
      "batch_size": 64,
      "probe_type": "mlp",
      "probe_hidden_size": [
        256
      ],
      "num_classes": 2,
      "init_strategy": "gamma",
      "init_gamma": 2.0,
      "optimizer": "adamw",
      "train_epochs": 10,
      "lr": 0.001,
      "seed": 142,
      "early_stopping_gap": 3,
      "split_num": 5,
      "split_ratio": 2.0
    },
    "out_dir": "init_results/llama/somo/hidden-256/seed-142/strategy-gamma/gamma-2.0/opt-adamw/2026-04-22_03-59-11"
  },
  "train_meta": {
    "dataset": "compling/somo",
    "split": "train",
    "text_col": "text",
    "model": "meta-llama/Meta-Llama-3.1-8B",
    "max_len": 64,
    "hidden_size": 4096,
    "num_hidden_layers": 32,
    "num_states": 33,
    "memmap_file": "last_token_hidden_states.memmap",
    "dtype": "float32",
    "shape": [
      15000,
      33,
      4096
    ]
  },
  "test_meta": {
    "dataset": "compling/somo",
    "split": "test",
    "text_col": "text",
    "model": "meta-llama/Meta-Llama-3.1-8B",
    "max_len": 64,
    "hidden_size": 4096,
    "num_hidden_layers": 32,
    "num_states": 33,
    "memmap_file": "last_token_hidden_states.memmap",
    "dtype": "float32",
    "shape": [
      10000,
      33,
      4096
    ]
  },
  "splits": [
    484,
    968,
    1936,
    3872,
    7740
  ],
  "mdl_sum_ce": {
    "0": 10062.648302078247,
    "1": 10061.193881988525,
    "2": 10059.61254310608,
    "3": 10023.573472976685,
    "4": 9752.312936782837,
    "5": 9544.379848957062,
    "6": 9514.054717063904,
    "7": 9184.626463890076,
    "8": 8870.108583450317,
    "9": 8532.864830493927,
    "10": 8065.913882732391,
    "11": 8066.661080360413,
    "12": 8149.157256603241,
    "13": 8084.2868819236755,
    "14": 8190.617573738098,
    "15": 8291.614163398743,
    "16": 8440.095291614532,
    "17": 8431.737322330475,
    "18": 8439.636711597443,
    "19": 8605.54193019867,
    "20": 8563.038637638092,
    "21": 8644.929650783539,
    "22": 8663.22065114975,
    "23": 8751.359998226166,
    "24": 8798.758778572083,
    "25": 8802.991924285889,
    "26": 8799.789377212524,
    "27": 8808.081525802612,
    "28": 8839.744665145874,
    "29": 8923.27059173584,
    "30": 8839.399998664856,
    "31": 8782.43304347992,
    "32": 9007.401364326477
  },
  "mdl_nll": {
    "0": 0.6932108226838142,
    "1": 0.6931106284092399,
    "2": 0.6930016907623366,
    "3": 0.6905189771959689,
    "4": 0.6718319741514768,
    "5": 0.6575075674398637,
    "6": 0.6554184842287065,
    "7": 0.6327243361731935,
    "8": 0.611057356258633,
    "9": 0.5878248023211579,
    "10": 0.5556567844263152,
    "11": 0.5557082584982374,
    "12": 0.5613913789338137,
    "13": 0.5569224911768859,
    "14": 0.5642475595024867,
    "15": 0.5712051641911506,
    "16": 0.5814339550574905,
    "17": 0.5808581787221324,
    "18": 0.5814023637088346,
    "19": 0.5928314914713881,
    "20": 0.5899034608458317,
    "21": 0.5955448918974606,
    "22": 0.5968049497898698,
    "23": 0.6028768254495843,
    "24": 0.6061421037869994,
    "25": 0.6064337230838998,
    "26": 0.6062131012133181,
    "27": 0.6067843431938973,
    "28": 0.6089656010709475,
    "29": 0.61471966049434,
    "30": 0.608941857168976,
    "31": 0.6050174320391237,
    "32": 0.6205153874570458
  },
  "stopping_epochs_per_stage": {
    "0": [
      1,
      5,
      10,
      3
    ],
    "1": [
      6,
      2,
      3,
      1
    ],
    "2": [
      7,
      1,
      4,
      1
    ],
    "3": [
      8,
      2,
      9,
      10
    ],
    "4": [
      8,
      3,
      7,
      9
    ],
    "5": [
      8,
      10,
      9,
      10
    ],
    "6": [
      9,
      3,
      9,
      9
    ],
    "7": [
      10,
      9,
      10,
      8
    ],
    "8": [
      8,
      9,
      8,
      9
    ],
    "9": [
      10,
      8,
      10,
      10
    ],
    "10": [
      6,
      7,
      7,
      5
    ],
    "11": [
      8,
      9,
      4,
      6
    ],
    "12": [
      6,
      9,
      6,
      5
    ],
    "13": [
      10,
      4,
      6,
      4
    ],
    "14": [
      9,
      8,
      3,
      4
    ],
    "15": [
      8,
      8,
      4,
      3
    ],
    "16": [
      10,
      6,
      3,
      5
    ],
    "17": [
      6,
      10,
      4,
      6
    ],
    "18": [
      5,
      9,
      7,
      8
    ],
    "19": [
      10,
      8,
      5,
      6
    ],
    "20": [
      10,
      10,
      5,
      4
    ],
    "21": [
      5,
      5,
      4,
      4
    ],
    "22": [
      10,
      10,
      4,
      6
    ],
    "23": [
      5,
      10,
      9,
      5
    ],
    "24": [
      5,
      5,
      6,
      5
    ],
    "25": [
      3,
      5,
      6,
      5
    ],
    "26": [
      2,
      5,
      5,
      6
    ],
    "27": [
      5,
      7,
      7,
      9
    ],
    "28": [
      2,
      5,
      7,
      3
    ],
    "29": [
      2,
      5,
      7,
      5
    ],
    "30": [
      4,
      7,
      3,
      5
    ],
    "31": [
      3,
      9,
      5,
      7
    ],
    "32": [
      7,
      5,
      2,
      9
    ]
  },
  "test_acc": {
    "0": 0.5013,
    "1": 0.5013,
    "2": 0.5239,
    "3": 0.5533,
    "4": 0.6113,
    "5": 0.6367,
    "6": 0.6321,
    "7": 0.6623,
    "8": 0.6927,
    "9": 0.7062,
    "10": 0.7212,
    "11": 0.694,
    "12": 0.7328,
    "13": 0.7249,
    "14": 0.7234,
    "15": 0.7277,
    "16": 0.7164,
    "17": 0.719,
    "18": 0.7149,
    "19": 0.7108,
    "20": 0.704,
    "21": 0.7136,
    "22": 0.7195,
    "23": 0.7007,
    "24": 0.709,
    "25": 0.7004,
    "26": 0.6974,
    "27": 0.7026,
    "28": 0.7043,
    "29": 0.6757,
    "30": 0.7034,
    "31": 0.7034,
    "32": 0.6864
  },
  "test_loss": {
    "0": 0.6932975713729859,
    "1": 0.6931540697097779,
    "2": 0.6920314659118653,
    "3": 0.6858711287498475,
    "4": 0.6560890782356262,
    "5": 0.6408273232460022,
    "6": 0.6438621697425843,
    "7": 0.6184885057449341,
    "8": 0.5895036053657532,
    "9": 0.5738221129417419,
    "10": 0.5557214509010315,
    "11": 0.6067708147525788,
    "12": 0.5455608204364777,
    "13": 0.5491443330287933,
    "14": 0.5710434771537781,
    "15": 0.5439859118938446,
    "16": 0.5631976904869079,
    "17": 0.5597180006980896,
    "18": 0.5679022491455078,
    "19": 0.568237219953537,
    "20": 0.5831260956764222,
    "21": 0.5695864346504211,
    "22": 0.5611545961380004,
    "23": 0.5866604882240295,
    "24": 0.5655409421920776,
    "25": 0.5838947682380676,
    "26": 0.5908202342033386,
    "27": 0.5771850823402405,
    "28": 0.5745590397834778,
    "29": 0.60767696018219,
    "30": 0.5830297987937927,
    "31": 0.5767028148651123,
    "32": 0.597402126789093
  },
  "drift_final_total_l2": {
    "0": 3.4323747158050537,
    "1": 3.8016769886016846,
    "2": 15.167091369628906,
    "3": 12.828434944152832,
    "4": 13.158785820007324,
    "5": 25.177871704101562,
    "6": 29.658411026000977,
    "7": 17.268699645996094,
    "8": 10.98777961730957,
    "9": 23.149728775024414,
    "10": 27.324609756469727,
    "11": 28.775819778442383,
    "12": 23.593544006347656,
    "13": 35.32358169555664,
    "14": 31.344989776611328,
    "15": 23.851211547851562,
    "16": 33.260311126708984,
    "17": 21.846492767333984,
    "18": 21.787595748901367,
    "19": 25.07851219177246,
    "20": 13.15762996673584,
    "21": 24.97269058227539,
    "22": 23.41953468322754,
    "23": 19.73248291015625,
    "24": 12.545833587646484,
    "25": 18.472522735595703,
    "26": 13.649741172790527,
    "27": 10.960321426391602,
    "28": 10.532196044921875,
    "29": 19.277856826782227,
    "30": 13.889466285705566,
    "31": 9.845548629760742,
    "32": 18.29861831665039
  },
  "probe_type": "mlp",
  "probe_hidden_size": [
    256
  ],
  "init_strategy": "gamma",
  "init_gamma": 2.0,
  "effective_lr": 0.001,
  "lr_scaling_rule": "base_lr",
  "bias_init": "zero",
  "forward_prefactor": 1.0,
  "probe_width": 256,
  "L": 33,
  "D": 4096
}