{
  "config": {
    "model_short": "llama",
    "task_name": "somo",
    "dataset": {
      "train": "cache/llama/somo_train/",
      "test": "cache/llama/somo_test/"
    },
    "mdl": {
      "batch_size": 64,
      "probe_type": "mlp",
      "probe_hidden_size": [
        1024
      ],
      "num_classes": 2,
      "init_strategy": "mup",
      "init_gamma": null,
      "optimizer": "adam",
      "train_epochs": 20,
      "lr": 0.0009765625,
      "seed": 242,
      "early_stopping_gap": 3,
      "split_num": 5,
      "split_ratio": 2.0
    },
    "out_dir": "muP_results/llama/somo/hidden-1024/seed-242/strategy-mup/opt-adam/2026-04-28_20-11-48"
  },
  "train_meta": {
    "dataset": "compling/somo",
    "split": "train",
    "text_col": "text",
    "model": "meta-llama/Meta-Llama-3.1-8B",
    "max_len": 64,
    "hidden_size": 4096,
    "num_hidden_layers": 32,
    "num_states": 33,
    "memmap_file": "last_token_hidden_states.memmap",
    "dtype": "float32",
    "shape": [
      15000,
      33,
      4096
    ]
  },
  "test_meta": {
    "dataset": "compling/somo",
    "split": "test",
    "text_col": "text",
    "model": "meta-llama/Meta-Llama-3.1-8B",
    "max_len": 64,
    "hidden_size": 4096,
    "num_hidden_layers": 32,
    "num_states": 33,
    "memmap_file": "last_token_hidden_states.memmap",
    "dtype": "float32",
    "shape": [
      10000,
      33,
      4096
    ]
  },
  "splits": [
    484,
    968,
    1936,
    3872,
    7740
  ],
  "mdl_sum_ce": {
    "0": 10061.63721036911,
    "1": 10060.925610542297,
    "2": 10060.074304580688,
    "3": 10011.409599781036,
    "4": 9724.696546554565,
    "5": 9467.546195030212,
    "6": 9396.644404888153,
    "7": 9194.19384098053,
    "8": 8866.740260124207,
    "9": 8497.287987232208,
    "10": 8065.3152232170105,
    "11": 8089.093472242355,
    "12": 8028.950425386429,
    "13": 8068.073593616486,
    "14": 8105.382518291473,
    "15": 8206.937245607376,
    "16": 8290.586926698685,
    "17": 8374.811428070068,
    "18": 8440.66724729538,
    "19": 8519.29405617714,
    "20": 8531.209578752518,
    "21": 8558.890032052994,
    "22": 8587.89243888855,
    "23": 8638.492070674896,
    "24": 8678.126424312592,
    "25": 8689.38629245758,
    "26": 8696.239998817444,
    "27": 8669.09155035019,
    "28": 8714.245748519897,
    "29": 8734.434772491455,
    "30": 8807.90779876709,
    "31": 8672.52128982544,
    "32": 8921.53744316101
  },
  "mdl_nll": {
    "0": 0.6931411690802639,
    "1": 0.6930921473231122,
    "2": 0.6930335012800144,
    "3": 0.689681014038374,
    "4": 0.6699294948026017,
    "5": 0.6522145353423955,
    "6": 0.6473301463824851,
    "7": 0.63338342800913,
    "8": 0.6108253141446822,
    "9": 0.585373931333164,
    "10": 0.555615543070888,
    "11": 0.5572536147866048,
    "12": 0.5531103902856455,
    "13": 0.5558055658319431,
    "14": 0.5583757590446041,
    "15": 0.565371813557962,
    "16": 0.5711343983672282,
    "17": 0.5769365822588914,
    "18": 0.5814733567990755,
    "19": 0.5868899184470335,
    "20": 0.5877107728542654,
    "21": 0.5896176654762327,
    "22": 0.591615626817894,
    "23": 0.5951014102145836,
    "24": 0.5978318010686547,
    "25": 0.5986074877691913,
    "26": 0.5990796361819678,
    "27": 0.5972093931076184,
    "28": 0.6003200432984223,
    "29": 0.6017108550903455,
    "30": 0.6067723752250682,
    "31": 0.5974456661494516,
    "32": 0.6146002647534452
  },
  "stopping_epochs_per_stage": {
    "0": [
      6,
      3,
      1,
      1
    ],
    "1": [
      20,
      4,
      1,
      19
    ],
    "2": [
      6,
      11,
      1,
      2
    ],
    "3": [
      2,
      2,
      1,
      20
    ],
    "4": [
      20,
      5,
      20,
      20
    ],
    "5": [
      20,
      19,
      19,
      20
    ],
    "6": [
      19,
      19,
      20,
      19
    ],
    "7": [
      20,
      20,
      20,
      20
    ],
    "8": [
      19,
      20,
      18,
      13
    ],
    "9": [
      19,
      18,
      20,
      15
    ],
    "10": [
      20,
      20,
      13,
      19
    ],
    "11": [
      20,
      19,
      10,
      10
    ],
    "12": [
      20,
      19,
      19,
      19
    ],
    "13": [
      20,
      19,
      20,
      14
    ],
    "14": [
      20,
      20,
      19,
      15
    ],
    "15": [
      20,
      14,
      16,
      17
    ],
    "16": [
      19,
      11,
      17,
      12
    ],
    "17": [
      20,
      16,
      16,
      14
    ],
    "18": [
      20,
      18,
      17,
      13
    ],
    "19": [
      19,
      19,
      11,
      10
    ],
    "20": [
      18,
      18,
      20,
      8
    ],
    "21": [
      20,
      18,
      12,
      11
    ],
    "22": [
      16,
      13,
      16,
      12
    ],
    "23": [
      16,
      18,
      19,
      11
    ],
    "24": [
      15,
      18,
      16,
      10
    ],
    "25": [
      6,
      17,
      16,
      8
    ],
    "26": [
      13,
      11,
      15,
      10
    ],
    "27": [
      12,
      16,
      14,
      13
    ],
    "28": [
      12,
      7,
      11,
      10
    ],
    "29": [
      14,
      15,
      11,
      9
    ],
    "30": [
      3,
      6,
      7,
      6
    ],
    "31": [
      13,
      8,
      11,
      9
    ],
    "32": [
      5,
      9,
      8,
      5
    ]
  },
  "test_acc": {
    "0": 0.5013,
    "1": 0.4963,
    "2": 0.521,
    "3": 0.5512,
    "4": 0.5903,
    "5": 0.6383,
    "6": 0.6546,
    "7": 0.6696,
    "8": 0.6907,
    "9": 0.7078,
    "10": 0.7307,
    "11": 0.7253,
    "12": 0.7321,
    "13": 0.7348,
    "14": 0.7298,
    "15": 0.7324,
    "16": 0.7275,
    "17": 0.7299,
    "18": 0.7246,
    "19": 0.7223,
    "20": 0.722,
    "21": 0.7195,
    "22": 0.6995,
    "23": 0.6967,
    "24": 0.711,
    "25": 0.7128,
    "26": 0.7115,
    "27": 0.7056,
    "28": 0.7038,
    "29": 0.7007,
    "30": 0.7003,
    "31": 0.6999,
    "32": 0.6865
  },
  "test_loss": {
    "0": 0.6933068046569825,
    "1": 0.6934641326904297,
    "2": 0.6916735511779785,
    "3": 0.6840630609512329,
    "4": 0.6717271508216858,
    "5": 0.6349075135231018,
    "6": 0.6271293375015259,
    "7": 0.6107416429519653,
    "8": 0.5865413206100464,
    "9": 0.5760054029464722,
    "10": 0.5374964656829834,
    "11": 0.5490617950439454,
    "12": 0.5346077970027924,
    "13": 0.5318106781482697,
    "14": 0.5420105429649353,
    "15": 0.541003019285202,
    "16": 0.5409526231765747,
    "17": 0.5444685616970062,
    "18": 0.5503139904022217,
    "19": 0.5552426320075988,
    "20": 0.5556589894294739,
    "21": 0.5554442796230317,
    "22": 0.5779190421104431,
    "23": 0.5852178220748901,
    "24": 0.569370442199707,
    "25": 0.567706690979004,
    "26": 0.5669561838150025,
    "27": 0.5792525000572205,
    "28": 0.5814273650169373,
    "29": 0.5795121662139893,
    "30": 0.5849949806213379,
    "31": 0.5750978086948395,
    "32": 0.6062262447357177
  },
  "drift_final_total_l2": {
    "0": 13.956870079040527,
    "1": 99.32412719726562,
    "2": 132.93138122558594,
    "3": 184.1806182861328,
    "4": 234.79844665527344,
    "5": 227.14993286132812,
    "6": 224.90875244140625,
    "7": 243.78240966796875,
    "8": 248.73646545410156,
    "9": 246.06631469726562,
    "10": 244.55931091308594,
    "11": 243.0265655517578,
    "12": 243.7216339111328,
    "13": 238.7333221435547,
    "14": 237.00234985351562,
    "15": 220.08541870117188,
    "16": 210.1270751953125,
    "17": 197.04734802246094,
    "18": 199.22398376464844,
    "19": 186.07647705078125,
    "20": 166.5560302734375,
    "21": 177.0545196533203,
    "22": 185.19219970703125,
    "23": 171.42465209960938,
    "24": 167.73684692382812,
    "25": 158.5155029296875,
    "26": 158.6827392578125,
    "27": 150.31747436523438,
    "28": 154.32431030273438,
    "29": 148.9819793701172,
    "30": 150.47764587402344,
    "31": 105.06364440917969,
    "32": 121.82965850830078
  },
  "probe_type": "mlp",
  "probe_hidden_size": [
    1024
  ],
  "init_strategy": "mup",
  "init_gamma": null,
  "effective_lr": {
    "hidden": 0.0009765625,
    "readout": 9.5367431640625e-07
  },
  "lr_scaling_rule": "hidden=base_lr,readout=base_lr*(1/width)",
  "bias_init": "zero",
  "forward_prefactor": 1.0,
  "probe_width": 1024,
  "L": 33,
  "D": 4096
}