{
  "config": {
    "model_short": "llama",
    "task_name": "somo",
    "dataset": {
      "train": "cache/llama/somo_train/",
      "test": "cache/llama/somo_test/"
    },
    "mdl": {
      "batch_size": 64,
      "probe_type": "mlp",
      "probe_hidden_size": [
        128
      ],
      "num_classes": 2,
      "init_strategy": "gamma_first_zero",
      "init_gamma": 0.5,
      "optimizer": "adamw",
      "train_epochs": 10,
      "lr": 0.001,
      "seed": 342,
      "early_stopping_gap": 3,
      "split_num": 5,
      "split_ratio": 2.0
    },
    "out_dir": "init_results/llama/somo/hidden-128/seed-342/strategy-gamma_first_zero/gamma-0.5/2026-04-20_23-35-57"
  },
  "train_meta": {
    "dataset": "compling/somo",
    "split": "train",
    "text_col": "text",
    "model": "meta-llama/Meta-Llama-3.1-8B",
    "max_len": 64,
    "hidden_size": 4096,
    "num_hidden_layers": 32,
    "num_states": 33,
    "memmap_file": "last_token_hidden_states.memmap",
    "dtype": "float32",
    "shape": [
      15000,
      33,
      4096
    ]
  },
  "test_meta": {
    "dataset": "compling/somo",
    "split": "test",
    "text_col": "text",
    "model": "meta-llama/Meta-Llama-3.1-8B",
    "max_len": 64,
    "hidden_size": 4096,
    "num_hidden_layers": 32,
    "num_states": 33,
    "memmap_file": "last_token_hidden_states.memmap",
    "dtype": "float32",
    "shape": [
      10000,
      33,
      4096
    ]
  },
  "splits": [
    484,
    968,
    1936,
    3872,
    7740
  ],
  "mdl_sum_ce": {
    "0": 10060.815231323242,
    "1": 10060.821514606476,
    "2": 10060.82238483429,
    "3": 10060.824003696442,
    "4": 10060.827290058136,
    "5": 10060.823011398315,
    "6": 10060.827281951904,
    "7": 10060.829067707062,
    "8": 10060.84824848175,
    "9": 10060.814672470093,
    "10": 10060.817574977875,
    "11": 10060.839692115784,
    "12": 10060.847319602966,
    "13": 10060.852153778076,
    "14": 10060.823077201843,
    "15": 10060.819563388824,
    "16": 10060.8445520401,
    "17": 10060.846406459808,
    "18": 10060.814535140991,
    "19": 10060.839408397675,
    "20": 10060.82625579834,
    "21": 10060.814022064209,
    "22": 10060.903718948364,
    "23": 10060.81523513794,
    "24": 10060.827471733093,
    "25": 10060.820553779602,
    "26": 10060.818211078644,
    "27": 10060.828479290009,
    "28": 10060.823483467102,
    "29": 10060.841995239258,
    "30": 10060.837096691132,
    "31": 10060.815559387207,
    "32": 10060.81876707077
  },
  "mdl_nll": {
    "0": 0.6930845433537642,
    "1": 0.6930849762060124,
    "2": 0.6930850361555725,
    "3": 0.6930851476781786,
    "4": 0.6930853740739967,
    "5": 0.6930850793192557,
    "6": 0.6930853735155624,
    "7": 0.6930854965353446,
    "8": 0.6930868178893462,
    "9": 0.6930845048546496,
    "10": 0.6930847048069629,
    "11": 0.6930862284455624,
    "12": 0.6930867538993501,
    "13": 0.6930870869232624,
    "14": 0.6930850838524278,
    "15": 0.6930848417876015,
    "16": 0.6930865632433246,
    "17": 0.6930866909933734,
    "18": 0.6930844953941162,
    "19": 0.6930862089003633,
    "20": 0.6930853028243552,
    "21": 0.6930844600485127,
    "22": 0.6930906392221249,
    "23": 0.6930845436165569,
    "24": 0.6930853865894939,
    "25": 0.6930849100151283,
    "26": 0.6930847486276277,
    "27": 0.6930854559995873,
    "28": 0.6930851118398389,
    "29": 0.6930863871065899,
    "30": 0.6930860496480526,
    "31": 0.6930845659539272,
    "32": 0.693084786929648
  },
  "stopping_epochs_per_stage": {
    "0": [
      8,
      1,
      1,
      2
    ],
    "1": [
      9,
      1,
      1,
      2
    ],
    "2": [
      10,
      1,
      1,
      2
    ],
    "3": [
      10,
      2,
      1,
      2
    ],
    "4": [
      9,
      2,
      1,
      5
    ],
    "5": [
      10,
      1,
      1,
      2
    ],
    "6": [
      10,
      2,
      1,
      3
    ],
    "7": [
      10,
      2,
      2,
      4
    ],
    "8": [
      10,
      1,
      1,
      2
    ],
    "9": [
      10,
      1,
      1,
      5
    ],
    "10": [
      9,
      1,
      1,
      2
    ],
    "11": [
      10,
      2,
      2,
      2
    ],
    "12": [
      7,
      2,
      1,
      2
    ],
    "13": [
      10,
      1,
      1,
      2
    ],
    "14": [
      10,
      1,
      1,
      2
    ],
    "15": [
      9,
      2,
      1,
      5
    ],
    "16": [
      9,
      1,
      1,
      2
    ],
    "17": [
      8,
      1,
      2,
      4
    ],
    "18": [
      8,
      1,
      1,
      2
    ],
    "19": [
      10,
      1,
      1,
      4
    ],
    "20": [
      8,
      1,
      1,
      5
    ],
    "21": [
      10,
      1,
      1,
      10
    ],
    "22": [
      7,
      2,
      1,
      5
    ],
    "23": [
      10,
      2,
      1,
      9
    ],
    "24": [
      10,
      2,
      1,
      2
    ],
    "25": [
      10,
      1,
      1,
      3
    ],
    "26": [
      10,
      1,
      1,
      2
    ],
    "27": [
      9,
      1,
      1,
      3
    ],
    "28": [
      10,
      1,
      1,
      5
    ],
    "29": [
      9,
      1,
      1,
      3
    ],
    "30": [
      10,
      1,
      1,
      1
    ],
    "31": [
      10,
      2,
      1,
      4
    ],
    "32": [
      7,
      1,
      1,
      2
    ]
  },
  "test_acc": {
    "0": 0.5013,
    "1": 0.5013,
    "2": 0.5013,
    "3": 0.5013,
    "4": 0.5013,
    "5": 0.5013,
    "6": 0.5013,
    "7": 0.5013,
    "8": 0.5013,
    "9": 0.5013,
    "10": 0.5013,
    "11": 0.5013,
    "12": 0.5013,
    "13": 0.5013,
    "14": 0.5013,
    "15": 0.5013,
    "16": 0.5013,
    "17": 0.5013,
    "18": 0.5013,
    "19": 0.5013,
    "20": 0.5013,
    "21": 0.5013,
    "22": 0.5013,
    "23": 0.5013,
    "24": 0.5013,
    "25": 0.5013,
    "26": 0.5013,
    "27": 0.5013,
    "28": 0.5013,
    "29": 0.5013,
    "30": 0.5013,
    "31": 0.5013,
    "32": 0.5013
  },
  "test_loss": {
    "0": 0.6932300228118896,
    "1": 0.6931742406845093,
    "2": 0.693177020072937,
    "3": 0.6931903774261474,
    "4": 0.6932143072128296,
    "5": 0.6932839422225953,
    "6": 0.6931668822288514,
    "7": 0.6932566057205201,
    "8": 0.6931803119659424,
    "9": 0.6931822579383851,
    "10": 0.6931958025932312,
    "11": 0.6931785649299621,
    "12": 0.6932887954711914,
    "13": 0.6931441464424133,
    "14": 0.6932553541183472,
    "15": 0.6932197501182557,
    "16": 0.693220961856842,
    "17": 0.6931584723472595,
    "18": 0.6931497205734253,
    "19": 0.6931439702987671,
    "20": 0.6932039375305176,
    "21": 0.6931907371520996,
    "22": 0.6931520913124084,
    "23": 0.6932424531936645,
    "24": 0.6931609691619873,
    "25": 0.6931440705299378,
    "26": 0.69316748046875,
    "27": 0.6932960761070251,
    "28": 0.6931703995704651,
    "29": 0.6931846179962158,
    "30": 0.6931440430641175,
    "31": 0.6931563257217407,
    "32": 0.6931964505195618
  },
  "drift_final_total_l2": {
    "0": 0.03521587699651718,
    "1": 0.016292769461870193,
    "2": 0.030684368684887886,
    "3": 0.02192172408103943,
    "4": 0.024846108630299568,
    "5": 0.03539999946951866,
    "6": 0.014678162522614002,
    "7": 0.028056100010871887,
    "8": 0.01874345727264881,
    "9": 0.01883603073656559,
    "10": 0.01931009255349636,
    "11": 0.025946317240595818,
    "12": 0.030800115317106247,
    "13": 0.017002051696181297,
    "14": 0.03127627819776535,
    "15": 0.023366814479231834,
    "16": 0.023373154923319817,
    "17": 0.02514532208442688,
    "18": 0.01865229383111,
    "19": 0.01851239614188671,
    "20": 0.02030743472278118,
    "21": 0.026500113308429718,
    "22": 0.02032965049147606,
    "23": 0.029962975531816483,
    "24": 0.013486071489751339,
    "25": 0.02574368380010128,
    "26": 0.01931161992251873,
    "27": 0.02853202447295189,
    "28": 0.021028609946370125,
    "29": 0.023172086104750633,
    "30": 0.020520953461527824,
    "31": 0.01722700335085392,
    "32": 0.02252809889614582
  },
  "probe_type": "mlp",
  "probe_hidden_size": [
    128
  ],
  "init_strategy": "gamma_first_zero",
  "init_gamma": 0.5,
  "effective_lr": 0.001,
  "lr_scaling_rule": "base_lr",
  "bias_init": "zero",
  "forward_prefactor": 1.0,
  "probe_width": 128,
  "L": 33,
  "D": 4096
}