{
  "config": {
    "model_short": "llama",
    "task_name": "somo",
    "dataset": {
      "train": "cache/llama/somo_train/",
      "test": "cache/llama/somo_test/"
    },
    "mdl": {
      "batch_size": 64,
      "probe_type": "mlp",
      "probe_hidden_size": [
        181
      ],
      "num_classes": 2,
      "init_strategy": "gamma_second_zero",
      "init_gamma": 2.0,
      "optimizer": "adamw",
      "train_epochs": 10,
      "lr": 0.001,
      "seed": 342,
      "early_stopping_gap": 3,
      "split_num": 5,
      "split_ratio": 2.0
    },
    "out_dir": "init_results/llama/somo/hidden-181/seed-342/strategy-gamma_second_zero/gamma-2.0/opt-adamw/2026-04-25_03-07-25"
  },
  "train_meta": {
    "dataset": "compling/somo",
    "split": "train",
    "text_col": "text",
    "model": "meta-llama/Meta-Llama-3.1-8B",
    "max_len": 64,
    "hidden_size": 4096,
    "num_hidden_layers": 32,
    "num_states": 33,
    "memmap_file": "last_token_hidden_states.memmap",
    "dtype": "float32",
    "shape": [
      15000,
      33,
      4096
    ]
  },
  "test_meta": {
    "dataset": "compling/somo",
    "split": "test",
    "text_col": "text",
    "model": "meta-llama/Meta-Llama-3.1-8B",
    "max_len": 64,
    "hidden_size": 4096,
    "num_hidden_layers": 32,
    "num_states": 33,
    "memmap_file": "last_token_hidden_states.memmap",
    "dtype": "float32",
    "shape": [
      10000,
      33,
      4096
    ]
  },
  "splits": [
    484,
    968,
    1936,
    3872,
    7740
  ],
  "mdl_sum_ce": {
    "0": 10061.427654743195,
    "1": 10060.826884269714,
    "2": 10060.753069877625,
    "3": 10032.318816661835,
    "4": 9745.280181407928,
    "5": 9878.29139137268,
    "6": 9421.309599399567,
    "7": 9267.051027297974,
    "8": 8909.635594844818,
    "9": 8436.568227767944,
    "10": 8073.379395246506,
    "11": 8044.999430656433,
    "12": 8026.713495254517,
    "13": 8092.142826795578,
    "14": 8126.32497882843,
    "15": 8299.297811031342,
    "16": 8340.090894699097,
    "17": 8405.89441871643,
    "18": 8455.175423622131,
    "19": 8603.81287574768,
    "20": 8574.132580757141,
    "21": 8607.174079418182,
    "22": 8594.57459449768,
    "23": 8778.95768737793,
    "24": 8689.805018424988,
    "25": 8763.959859848022,
    "26": 8712.794840812683,
    "27": 8777.776275634766,
    "28": 8752.52165222168,
    "29": 8800.039431095123,
    "30": 8834.138920783997,
    "31": 8725.734607696533,
    "32": 8929.376981258392
  },
  "mdl_nll": {
    "0": 0.6931267328977125,
    "1": 0.6930853461194347,
    "2": 0.6930802610827793,
    "3": 0.6911214395606113,
    "4": 0.6713474911413563,
    "5": 0.6805105670551584,
    "6": 0.6490293193303642,
    "7": 0.6384025232362892,
    "8": 0.6137803523591084,
    "9": 0.5811909773882574,
    "10": 0.5561710798599135,
    "11": 0.5542159982540943,
    "12": 0.5529562892845492,
    "13": 0.5574636833008803,
    "14": 0.5598184747057336,
    "15": 0.5717344868442644,
    "16": 0.5745447020321781,
    "17": 0.5790778739815673,
    "18": 0.5824728178301275,
    "19": 0.5927123777726426,
    "20": 0.5906677170540879,
    "21": 0.5929439294170696,
    "22": 0.5920759571850152,
    "23": 0.6047780164906262,
    "24": 0.5986363335922422,
    "25": 0.6037448236324072,
    "26": 0.600220090990127,
    "27": 0.6046966296248805,
    "28": 0.6029568512139487,
    "29": 0.6062303273005734,
    "30": 0.6085794241377788,
    "31": 0.6011115050769175,
    "32": 0.615140326622926
  },
  "stopping_epochs_per_stage": {
    "0": [
      2,
      1,
      1,
      1
    ],
    "1": [
      2,
      1,
      1,
      2
    ],
    "2": [
      2,
      1,
      4,
      4
    ],
    "3": [
      2,
      1,
      10,
      10
    ],
    "4": [
      3,
      1,
      9,
      7
    ],
    "5": [
      4,
      6,
      10,
      5
    ],
    "6": [
      4,
      10,
      7,
      9
    ],
    "7": [
      5,
      9,
      5,
      9
    ],
    "8": [
      9,
      9,
      10,
      9
    ],
    "9": [
      8,
      10,
      5,
      10
    ],
    "10": [
      8,
      7,
      8,
      5
    ],
    "11": [
      9,
      8,
      8,
      6
    ],
    "12": [
      9,
      10,
      7,
      9
    ],
    "13": [
      8,
      5,
      5,
      9
    ],
    "14": [
      9,
      7,
      8,
      8
    ],
    "15": [
      10,
      5,
      5,
      4
    ],
    "16": [
      4,
      8,
      6,
      10
    ],
    "17": [
      6,
      6,
      4,
      5
    ],
    "18": [
      4,
      6,
      7,
      7
    ],
    "19": [
      10,
      9,
      6,
      5
    ],
    "20": [
      6,
      5,
      5,
      8
    ],
    "21": [
      8,
      7,
      6,
      9
    ],
    "22": [
      5,
      10,
      7,
      5
    ],
    "23": [
      5,
      5,
      6,
      3
    ],
    "24": [
      5,
      8,
      10,
      7
    ],
    "25": [
      4,
      5,
      4,
      7
    ],
    "26": [
      4,
      8,
      5,
      6
    ],
    "27": [
      3,
      5,
      4,
      7
    ],
    "28": [
      9,
      4,
      5,
      5
    ],
    "29": [
      4,
      5,
      6,
      8
    ],
    "30": [
      4,
      9,
      4,
      5
    ],
    "31": [
      3,
      4,
      3,
      9
    ],
    "32": [
      4,
      4,
      4,
      9
    ]
  },
  "test_acc": {
    "0": 0.4982,
    "1": 0.5014,
    "2": 0.5013,
    "3": 0.5353,
    "4": 0.6113,
    "5": 0.6315,
    "6": 0.6525,
    "7": 0.667,
    "8": 0.6849,
    "9": 0.7023,
    "10": 0.7313,
    "11": 0.7124,
    "12": 0.7257,
    "13": 0.7349,
    "14": 0.7316,
    "15": 0.7311,
    "16": 0.7037,
    "17": 0.7251,
    "18": 0.7067,
    "19": 0.6885,
    "20": 0.7238,
    "21": 0.7141,
    "22": 0.7111,
    "23": 0.7099,
    "24": 0.7025,
    "25": 0.7039,
    "26": 0.6926,
    "27": 0.7047,
    "28": 0.6999,
    "29": 0.6879,
    "30": 0.699,
    "31": 0.6943,
    "32": 0.692
  },
  "test_loss": {
    "0": 0.6932902711868286,
    "1": 0.6932397644042969,
    "2": 0.693156097316742,
    "3": 0.6937321891784668,
    "4": 0.6565028310775757,
    "5": 0.6419067063331604,
    "6": 0.6273261507034302,
    "7": 0.6127126300811767,
    "8": 0.6000759222030639,
    "9": 0.5858667110443115,
    "10": 0.5407406876564026,
    "11": 0.5793369720458984,
    "12": 0.5488354391098023,
    "13": 0.5449128813266754,
    "14": 0.5427395174026489,
    "15": 0.5435388019561768,
    "16": 0.5764321012496948,
    "17": 0.5480181536197662,
    "18": 0.5810677179336547,
    "19": 0.5938341372489929,
    "20": 0.5574755525112152,
    "21": 0.5641752401351928,
    "22": 0.5679177165985108,
    "23": 0.5689575399398804,
    "24": 0.5853829424381256,
    "25": 0.5776140897750854,
    "26": 0.5922328914642334,
    "27": 0.576193796157837,
    "28": 0.5816860692977905,
    "29": 0.6068702119827271,
    "30": 0.5839767904281616,
    "31": 0.5809367392539978,
    "32": 0.5934471252441407
  },
  "drift_final_total_l2": {
    "0": 3.50445556640625,
    "1": 12.8438720703125,
    "2": 4.889220714569092,
    "3": 12.85873031616211,
    "4": 21.088945388793945,
    "5": 19.962921142578125,
    "6": 25.36189079284668,
    "7": 15.091312408447266,
    "8": 30.84152603149414,
    "9": 25.70072364807129,
    "10": 20.154939651489258,
    "11": 24.695356369018555,
    "12": 32.98165512084961,
    "13": 30.620899200439453,
    "14": 18.714569091796875,
    "15": 15.186399459838867,
    "16": 25.25063133239746,
    "17": 21.296533584594727,
    "18": 25.618207931518555,
    "19": 19.51954460144043,
    "20": 10.994495391845703,
    "21": 21.33442497253418,
    "22": 24.105899810791016,
    "23": 23.78221321105957,
    "24": 21.520565032958984,
    "25": 12.022381782531738,
    "26": 14.866401672363281,
    "27": 15.769265174865723,
    "28": 19.433168411254883,
    "29": 14.754047393798828,
    "30": 17.21662139892578,
    "31": 20.507427215576172,
    "32": 17.136398315429688
  },
  "probe_type": "mlp",
  "probe_hidden_size": [
    181
  ],
  "init_strategy": "gamma_second_zero",
  "init_gamma": 2.0,
  "effective_lr": 0.001,
  "lr_scaling_rule": "base_lr",
  "bias_init": "zero",
  "forward_prefactor": 1.0,
  "probe_width": 181,
  "L": 33,
  "D": 4096
}