{
  "config": {
    "model_short": "llama",
    "task_name": "somo",
    "dataset": {
      "train": "cache/llama/somo_train/",
      "test": "cache/llama/somo_test/"
    },
    "mdl": {
      "batch_size": 64,
      "probe_type": "mlp",
      "probe_hidden_size": [
        2048
      ],
      "num_classes": 2,
      "init_strategy": "gamma_second_zero",
      "init_gamma": 0.8,
      "optimizer": "adamw",
      "train_epochs": 10,
      "lr": 0.001,
      "seed": 42,
      "early_stopping_gap": 3,
      "split_num": 5,
      "split_ratio": 2.0
    },
    "out_dir": "init_results/llama/somo/hidden-2048/seed-42/strategy-gamma_second_zero/gamma-0.8/2026-04-21_01-33-17"
  },
  "train_meta": {
    "dataset": "compling/somo",
    "split": "train",
    "text_col": "text",
    "model": "meta-llama/Meta-Llama-3.1-8B",
    "max_len": 64,
    "hidden_size": 4096,
    "num_hidden_layers": 32,
    "num_states": 33,
    "memmap_file": "last_token_hidden_states.memmap",
    "dtype": "float32",
    "shape": [
      15000,
      33,
      4096
    ]
  },
  "test_meta": {
    "dataset": "compling/somo",
    "split": "test",
    "text_col": "text",
    "model": "meta-llama/Meta-Llama-3.1-8B",
    "max_len": 64,
    "hidden_size": 4096,
    "num_hidden_layers": 32,
    "num_states": 33,
    "memmap_file": "last_token_hidden_states.memmap",
    "dtype": "float32",
    "shape": [
      10000,
      33,
      4096
    ]
  },
  "splits": [
    484,
    968,
    1936,
    3872,
    7740
  ],
  "mdl_sum_ce": {
    "0": 10061.731767654419,
    "1": 10061.4033370018,
    "2": 10059.192676067352,
    "3": 10021.332777023315,
    "4": 9753.996752738953,
    "5": 9531.090922355652,
    "6": 9502.367286682129,
    "7": 9219.706512451172,
    "8": 8893.599347114563,
    "9": 8503.132279396057,
    "10": 8108.651387691498,
    "11": 8194.615726947784,
    "12": 8111.30899810791,
    "13": 8303.316978931427,
    "14": 8247.162261009216,
    "15": 8310.360088825226,
    "16": 8449.186954975128,
    "17": 8442.260280132294,
    "18": 8534.834300518036,
    "19": 8627.048081874847,
    "20": 8617.66747379303,
    "21": 8706.486161231995,
    "22": 8663.807657241821,
    "23": 8631.564070224762,
    "24": 8830.344581604004,
    "25": 8834.928713798523,
    "26": 8786.49127626419,
    "27": 8720.681355953217,
    "28": 8935.26591348648,
    "29": 8880.908337116241,
    "30": 8838.816311359406,
    "31": 8730.082747936249,
    "32": 8975.523920536041
  },
  "mdl_nll": {
    "0": 0.6931476830844874,
    "1": 0.6931250576606366,
    "2": 0.6929727663314517,
    "3": 0.6903646167693108,
    "4": 0.6719479713928735,
    "5": 0.6565920999142775,
    "6": 0.6546133429789287,
    "7": 0.6351409832220427,
    "8": 0.6126756232512099,
    "9": 0.5857765417054325,
    "10": 0.5586009498271906,
    "11": 0.5645229902829833,
    "12": 0.5587840312832675,
    "13": 0.5720113653163011,
    "14": 0.5681428948063665,
    "15": 0.5724965616440635,
    "16": 0.582060275211844,
    "17": 0.5815831000366695,
    "18": 0.5879604781288258,
    "19": 0.594313039533952,
    "20": 0.5936668141218676,
    "21": 0.5997854892003303,
    "22": 0.5968453883467775,
    "23": 0.5946241437189833,
    "24": 0.6083180340041336,
    "25": 0.6086338325846323,
    "26": 0.605297001671548,
    "27": 0.6007633890846801,
    "28": 0.6155460122269552,
    "29": 0.6118013459021936,
    "30": 0.6089016472416234,
    "31": 0.601411046289353,
    "32": 0.6183193662535162
  },
  "stopping_epochs_per_stage": {
    "0": [
      3,
      1,
      1,
      2
    ],
    "1": [
      1,
      2,
      2,
      1
    ],
    "2": [
      3,
      5,
      4,
      1
    ],
    "3": [
      2,
      5,
      5,
      6
    ],
    "4": [
      6,
      9,
      5,
      8
    ],
    "5": [
      1,
      8,
      6,
      7
    ],
    "6": [
      9,
      10,
      5,
      5
    ],
    "7": [
      10,
      8,
      6,
      7
    ],
    "8": [
      8,
      8,
      6,
      6
    ],
    "9": [
      6,
      6,
      5,
      4
    ],
    "10": [
      4,
      5,
      5,
      5
    ],
    "11": [
      7,
      5,
      4,
      2
    ],
    "12": [
      6,
      5,
      3,
      6
    ],
    "13": [
      3,
      5,
      2,
      3
    ],
    "14": [
      7,
      4,
      2,
      5
    ],
    "15": [
      6,
      2,
      5,
      5
    ],
    "16": [
      7,
      4,
      4,
      8
    ],
    "17": [
      5,
      3,
      3,
      6
    ],
    "18": [
      5,
      4,
      3,
      6
    ],
    "19": [
      5,
      3,
      7,
      3
    ],
    "20": [
      6,
      4,
      7,
      5
    ],
    "21": [
      3,
      5,
      3,
      5
    ],
    "22": [
      1,
      3,
      3,
      7
    ],
    "23": [
      5,
      8,
      5,
      5
    ],
    "24": [
      2,
      5,
      6,
      4
    ],
    "25": [
      4,
      4,
      4,
      4
    ],
    "26": [
      1,
      5,
      4,
      5
    ],
    "27": [
      1,
      7,
      5,
      5
    ],
    "28": [
      2,
      5,
      3,
      3
    ],
    "29": [
      3,
      6,
      2,
      6
    ],
    "30": [
      2,
      6,
      3,
      3
    ],
    "31": [
      5,
      5,
      5,
      5
    ],
    "32": [
      5,
      4,
      6,
      8
    ]
  },
  "test_acc": {
    "0": 0.5013,
    "1": 0.5017,
    "2": 0.5276,
    "3": 0.5494,
    "4": 0.608,
    "5": 0.6324,
    "6": 0.643,
    "7": 0.6619,
    "8": 0.6664,
    "9": 0.6886,
    "10": 0.7095,
    "11": 0.6782,
    "12": 0.7256,
    "13": 0.7272,
    "14": 0.7145,
    "15": 0.7012,
    "16": 0.7235,
    "17": 0.7012,
    "18": 0.7215,
    "19": 0.6996,
    "20": 0.7194,
    "21": 0.685,
    "22": 0.7037,
    "23": 0.6921,
    "24": 0.6849,
    "25": 0.6978,
    "26": 0.7097,
    "27": 0.6948,
    "28": 0.691,
    "29": 0.687,
    "30": 0.647,
    "31": 0.6851,
    "32": 0.6686
  },
  "test_loss": {
    "0": 0.6932272418022156,
    "1": 0.693602788734436,
    "2": 0.6924020136833191,
    "3": 0.6894093282699585,
    "4": 0.6596210765838623,
    "5": 0.6489580540657044,
    "6": 0.6360989966392517,
    "7": 0.6245978605270386,
    "8": 0.6382443679809571,
    "9": 0.6230067422866822,
    "10": 0.5868963774681091,
    "11": 0.6024682903289795,
    "12": 0.5735940071105957,
    "13": 0.5707333520174026,
    "14": 0.5818664382934571,
    "15": 0.6061863395690918,
    "16": 0.5702732848644256,
    "17": 0.6128913584232331,
    "18": 0.5651702058792114,
    "19": 0.5954216733932495,
    "20": 0.5639750101089478,
    "21": 0.6112606755256653,
    "22": 0.5889564418315888,
    "23": 0.5918982193946838,
    "24": 0.6147816581726074,
    "25": 0.5982688111305237,
    "26": 0.5881386647224426,
    "27": 0.6002407982826233,
    "28": 0.6021264149665833,
    "29": 0.6184637572288513,
    "30": 0.644028523349762,
    "31": 0.6084911727905273,
    "32": 0.6260142339229584
  },
  "drift_final_total_l2": {
    "0": 12.0595121383667,
    "1": 19.42489242553711,
    "2": 22.83012580871582,
    "3": 28.71537208557129,
    "4": 30.931482315063477,
    "5": 51.6179313659668,
    "6": 51.73159408569336,
    "7": 46.27342224121094,
    "8": 58.67634201049805,
    "9": 50.572853088378906,
    "10": 64.20933532714844,
    "11": 68.73613739013672,
    "12": 44.266597747802734,
    "13": 56.5396842956543,
    "14": 48.98732376098633,
    "15": 59.484195709228516,
    "16": 51.85452651977539,
    "17": 48.66730880737305,
    "18": 41.77309036254883,
    "19": 38.12683868408203,
    "20": 29.220857620239258,
    "21": 35.73067092895508,
    "22": 39.08116149902344,
    "23": 29.122238159179688,
    "24": 39.68754577636719,
    "25": 37.58287811279297,
    "26": 35.93257522583008,
    "27": 32.644229888916016,
    "28": 38.959800720214844,
    "29": 31.142335891723633,
    "30": 30.065736770629883,
    "31": 25.205907821655273,
    "32": 28.00830078125
  },
  "probe_type": "mlp",
  "probe_hidden_size": [
    2048
  ],
  "init_strategy": "gamma_second_zero",
  "init_gamma": 0.8,
  "effective_lr": 0.001,
  "lr_scaling_rule": "base_lr",
  "bias_init": "zero",
  "forward_prefactor": 1.0,
  "probe_width": 2048,
  "L": 33,
  "D": 4096
}